rinoh_typeface_dejavusansmono/AUTHORS
rinoh_typeface_dejavusansmono/BUGS
rinoh_typeface_dejavusansmono/DejaVuSansMono-Bold.ttf
rinoh_typeface_dejavusansmono/DejaVuSansMono-BoldOblique.ttf
rinoh_typeface_dejavusansmono/DejaVuSansMono-Oblique.ttf
rinoh_typeface_dejavusansmono/DejaVuSansMono.ttf
rinoh_typeface_dejavusansmono/LICENSE
rinoh_typeface_dejavusansmono/NEWS
rinoh_typeface_dejavusansmono/README.md
rinoh_typeface_dejavusansmono/__init__.py
rinoh_typeface_dejavusansmono/langcover.txt
rinoh_typeface_dejavusansmono/status.txt
rinoh_typeface_dejavusansmono/unicover.txt
rinoh_typeface_dejavusansmono-0.1.0.dist-info/METADATA
rinoh_typeface_dejavusansmono-0.1.0.dist-info/WHEEL
rinoh_typeface_dejavusansmono-0.1.0.dist-info/entry_points.txt
rinoh_typeface_dejavusansmono-0.1.0.dist-info/top_level.txt
rinoh_typeface_dejavusansmono-0.1.0.dist-info/RECORD
