Metadata-Version: 2.1
Name: rinoh-typeface-dejavusansmono
Version: 0.1.0
Summary: DejaVu Sans Mono typeface
Home-page: https://github.com/brechtm/rinoh-typeface-dejavusansmono
Author: Brecht Machiels
Author-email: brecht@mos6581.org
License: Bitstream Vera Fonts Copyright, Arev Fonts Copyright, Public Domain
Keywords: opentype font
Platform: UNKNOWN
Classifier: Intended Audience :: Developers
Classifier: Intended Audience :: End Users/Desktop
Classifier: Operating System :: OS Independent
Classifier: Programming Language :: Python
Classifier: Programming Language :: Python :: 3
Classifier: Topic :: Text Processing :: Fonts
Requires-Dist: rinohtype (>=0.4.3)
